[{"id":"d118e3200ed3a077","type":"mqtt in","z":"b25784ff8a20bc53","name":"","topic":"Vallox.RX","qos":"2","datatype":"auto-detect","broker":"fab3eeb5b50ff694","nl":false,"rap":true,"rh":0,"inputs":0,"x":360,"y":180,"wires":[["9b978b828aaf33d6"]]},{"id":"6864f0c886d0da87","type":"debug","z":"b25784ff8a20bc53","name":"error","active":false,"tosidebar":true,"console":false,"tostatus":false,"complete":"payload","targetType":"msg","statusVal":"","statusType":"auto","x":690,"y":280,"wires":[]},{"id":"9b978b828aaf33d6","type":"valloxrx","z":"b25784ff8a20bc53","description":"","x":520,"y":180,"wires":[["6d5620518a1e27db","4a68835f7baecd0c","ad29127f528b5e87"],["6864f0c886d0da87"]]},{"id":"6d5620518a1e27db","type":"vallox","z":"b25784ff8a20bc53","description":"Panel 1","receiver":"33","sendonnewdata":false,"x":680,"y":160,"wires":[["758d5039273c611d","48e70d6b251b9777"]]},{"id":"758d5039273c611d","type":"debug","z":"b25784ff8a20bc53","name":"panel 1","active":true,"tosidebar":true,"console":false,"tostatus":false,"complete":"payload","targetType":"msg","statusVal":"","statusType":"auto","x":880,"y":160,"wires":[]},{"id":"4a68835f7baecd0c","type":"debug","z":"b25784ff8a20bc53","name":"ok","active":false,"tosidebar":true,"console":false,"tostatus":false,"complete":"payload","targetType":"msg","statusVal":"","statusType":"auto","x":690,"y":240,"wires":[]},{"id":"ad29127f528b5e87","type":"vallox","z":"b25784ff8a20bc53","description":"Panel 2","receiver":"34","sendonnewdata":true,"x":680,"y":200,"wires":[["5d6e56965379dee1"]]},{"id":"5d6e56965379dee1","type":"debug","z":"b25784ff8a20bc53","name":"panel 2","active":false,"tosidebar":true,"console":false,"tostatus":false,"complete":"payload","targetType":"msg","statusVal":"","statusType":"auto","x":880,"y":200,"wires":[]},{"id":"2fe96892dfe1fd28","type":"http in","z":"b25784ff8a20bc53","name":"","url":"/vallox/panel1","method":"get","upload":false,"swaggerDoc":"","x":470,"y":100,"wires":[["6d5620518a1e27db"]]},{"id":"646fbe8c940969df","type":"http response","z":"b25784ff8a20bc53","name":"","statusCode":"","headers":{},"x":930,"y":100,"wires":[]},{"id":"48e70d6b251b9777","type":"function","z":"b25784ff8a20bc53","name":"json","func":"msg.headers = {};\nmsg.headers['content-type'] = 'application/json';\nreturn msg;","outputs":1,"noerr":0,"initialize":"","finalize":"","libs":[],"x":810,"y":100,"wires":[["646fbe8c940969df"]]},{"id":"fab3eeb5b50ff694","type":"mqtt-broker","name":"","broker":"unimatrix.fritz.box","port":"1883","clientid":"","autoConnect":true,"usetls":false,"protocolVersion":"4","keepalive":"60","cleansession":true,"birthTopic":"","birthQos":"0","birthPayload":"","birthMsg":{},"closeTopic":"","closeQos":"0","closePayload":"","closeMsg":{},"willTopic":"","willQos":"0","willPayload":"","willMsg":{},"userProps":"","sessionExpiry":""}]